base_manager/__init__.py
base_manager/base_manager.py
base_manager-0.0.1.dist-info/METADATA
base_manager-0.0.1.dist-info/WHEEL
base_manager-0.0.1.dist-info/licenses/LICENSE
base_manager-0.0.1.dist-info/RECORD
