Metadata-Version: 2.1
Name: base_manager
Version: 0.0.1
Summary: Use this little library for save your object in sqlite3.db with use two simple commadns: post, get.
Project-URL: Homepage, https://github.com/DanyaSh/base_manager
Project-URL: Bug Tracker, https://github.com/DanyaSh/base_manager/issues
Author-email: DanyaSh <danilashundeev@gmail.com>
License-File: LICENSE
Classifier: License :: OSI Approved :: MIT License
Classifier: Operating System :: OS Independent
Classifier: Programming Language :: Python :: 3
Requires-Python: >=3.7
